html2rss_ai/__init__.py
html2rss_ai/batch_processor.py
html2rss_ai/cli.py
html2rss_ai/extractor.py
html2rss_ai/schemas.py
html2rss_ai/utils/__init__.py
html2rss_ai/utils/config_loader.py
html2rss_ai/utils/date_utils.py
html2rss_ai/utils/logger_config.py
html2rss_ai-0.3.2.dist-info/METADATA
html2rss_ai-0.3.2.dist-info/WHEEL
html2rss_ai-0.3.2.dist-info/entry_points.txt
html2rss_ai-0.3.2.dist-info/licenses/LICENSE
html2rss_ai-0.3.2.dist-info/RECORD
