Metadata-Version: 2.4
Name: html2rss-ai
Version: 0.3.2
Summary: 🚀 AI-powered web scraping with modern CSS support. Extract content from any website using GPT-4, handles CSS Grid/Flexbox layouts, Tailwind CSS, and complex selectors automatically.
Project-URL: Homepage, https://github.com/mazzasaverio/html2rss-ai
Project-URL: Repository, https://github.com/mazzasaverio/html2rss-ai
Project-URL: Documentation, https://github.com/mazzasaverio/html2rss-ai#readme
Project-URL: Bug Tracker, https://github.com/mazzasaverio/html2rss-ai/issues
Project-URL: Changelog, https://github.com/mazzasaverio/html2rss-ai/blob/main/CHANGELOG.md
Project-URL: Source Code, https://github.com/mazzasaverio/html2rss-ai
Author-email: Saverio Mazza <saverio3107@gmail.com>
Maintainer-email: Saverio Mazza <saverio3107@gmail.com>
License: MIT
License-File: LICENSE
Keywords: ai-extraction,article-extraction,atom,content-extraction,css-grid,css-sanitization,css-selectors,feed-generation,flexbox,gpt-4,html-to-rss,javascript-sites,job-scraping,modern-css,openai,rss,rss-generator,smart-scraping,spa-scraping,tailwind-css,web-scraping,website-to-rss
Classifier: Development Status :: 4 - Beta
Classifier: Intended Audience :: Developers
Classifier: Intended Audience :: End Users/Desktop
Classifier: License :: OSI Approved :: MIT License
Classifier: Operating System :: OS Independent
Classifier: Programming Language :: Python :: 3
Classifier: Programming Language :: Python :: 3.10
Classifier: Programming Language :: Python :: 3.11
Classifier: Programming Language :: Python :: 3.12
Classifier: Programming Language :: Python :: 3.13
Classifier: Topic :: Internet :: WWW/HTTP
Classifier: Topic :: Software Development :: Libraries :: Python Modules
Classifier: Topic :: Text Processing :: Markup :: HTML
Classifier: Topic :: Text Processing :: Markup :: XML
Classifier: Topic :: Utilities
Requires-Python: >=3.10
Requires-Dist: beautifulsoup4>=4.12.3
Requires-Dist: click>=8.1.7
Requires-Dist: feedparser>=6.0.10
Requires-Dist: lxml>=5.2.2
Requires-Dist: pydantic>=2.9.0
Requires-Dist: requests>=2.32.3
Requires-Dist: typer[all]>=0.12.3
Requires-Dist: url2md4ai>=0.1.2
Provides-Extra: dev
Requires-Dist: black>=24.4.2; extra == 'dev'
Requires-Dist: ipykernel>=6.29.0; extra == 'dev'
Requires-Dist: jupyter>=1.0.0; extra == 'dev'
Requires-Dist: mypy>=1.14.0; extra == 'dev'
Requires-Dist: pre-commit>=4.0.0; extra == 'dev'
Requires-Dist: pytest-asyncio>=0.23.0; extra == 'dev'
Requires-Dist: pytest-cov>=4.0.0; extra == 'dev'
Requires-Dist: pytest-mock>=3.12.0; extra == 'dev'
Requires-Dist: pytest>=8.0.0; extra == 'dev'
Requires-Dist: ruff>=0.12.2; extra == 'dev'
Requires-Dist: url2md4ai; extra == 'dev'
Provides-Extra: playwright
Requires-Dist: playwright>=1.40.0; extra == 'playwright'
